[
  {
    "@context": "http://schema.org",
    "@type": "AdministrativeArea",
    "name": "East Midlands",
    "alternateName": "the East Midlands",
    "geoContains": [
      {
        "@type": "StadiumOrArena",
        "name": "Causeway Lane",
        "alternateName": "Proctor Cars Stadium",
        "maximumAttendeeCapacity": 2300,
        "latitude": 53.137031,
        "longitude": -1.551677,
        "subOrganization": {
          "@type": "SportsTeam",
          "name": "Matlock Town",
          "slogan": "The Gladiators",
          "memberOf": {
            "@type": "SportsOrganization",
            "name": "Northern Premier League"
          },
          "logo": {
            "@type": "ImageObject",
            "contentUrl": "https://media.api-sports.io/football/teams/7731.png",
            "caption": "Matlock Town crest",
            "representativeOfPage": true,
            "encodingFormat": "image/png",
            "width": 150,
            "height": 150
          }
        }
      },

      {
        "@type": "StadiumOrArena",
        "name": "Christchurch Meadow",
        "alternateName": "The Raygar Stadium",
        "maximumAttendeeCapacity": 2650,
        "latitude": 53.027196,
        "longitude": -1.487347,
        "subOrganization": {
          "@type": "SportsTeam",
          "name": "Belper Town",
          "slogan": "The Nailers",
          "memberOf": {
            "@type": "SportsOrganization",
            "name": "Northern Premier League"
          },
          "logo": {
            "@type": "ImageObject",
            "contentUrl": "https://media.api-sports.io/football/teams/7617.png",
            "caption": "Belper Town crest",
            "representativeOfPage": true,
            "encodingFormat": "image/png",
            "width": 150,
            "height": 150
          }
        }
      },

      {
        "@type": "StadiumOrArena",
        "name": "Jakemans Community Stadium",
        "maximumAttendeeCapacity": 5000,
        "latitude": 52.956335,
        "longitude": -0.028533,
        "subOrganization": {
          "@type": "SportsTeam",
          "name": "Boston United",
          "slogan": "The Pilgrims",
          "memberOf": {
            "@type": "SportsOrganization",
            "name": "National League North"
          },
          "logo": {
            "@type": "ImageObject",
            "contentUrl": "https://media.api-sports.io/football/teams/8146.png",
            "caption": "Boston United crest",
            "representativeOfPage": true,
            "encodingFormat": "image/png",
            "width": 150,
            "height": 150
          }
        }
      },

      {
        "@type": "StadiumOrArena",
        "name": "Latimer Park",
        "maximumAttendeeCapacity": 2400,
        "latitude": 52.366808,
        "longitude": -0.689305,
        "subOrganization": {
          "@type": "SportsTeam",
          "name": "Kettering Town",
          "slogan": "The Poppies",
          "memberOf": {
            "@type": "SportsOrganization",
            "name": "National League North"
          },
          "logo": {
            "@type": "ImageObject",
            "contentUrl": "https://media.api-sports.io/football/teams/8654.png",
            "caption": "Kettering Town crest",
            "representativeOfPage": true,
            "encodingFormat": "image/png",
            "width": 150,
            "height": 150
          }
        }
      },

      {
        "@type": "StadiumOrArena",
        "name": "Meadow Lane",
        "maximumAttendeeCapacity": 19841,
        "latitude": 52.942672,
        "longitude": -1.137151,
        "subOrganization": {
          "@type": "SportsTeam",
          "name": "Notts County",
          "slogan": "The Magpies",
          "memberOf": {
            "@type": "SportsOrganization",
            "name": "National League"
          },
          "logo": {
            "@type": "ImageObject",
            "contentUrl": "https://media.api-sports.io/football/teams/1376.png",
            "caption": "Notts County crest",
            "representativeOfPage": true,
            "encodingFormat": "image/png",
            "width": 150,
            "height": 150
          }
        }
      },

      {
        "@type": "StadiumOrArena",
        "name": "North Street",
        "alternateName": "Impact Arena Stadium",
        "maximumAttendeeCapacity": 3600,
        "latitude": 53.094516,
        "longitude": -1.381251,
        "subOrganization": {
          "@type": "SportsTeam",
          "name": "Alfreton Town",
          "slogan": "The Reds",
          "memberOf": {
            "@type": "SportsOrganization",
            "name": "National League North"
          },
          "logo": {
            "@type": "ImageObject",
            "contentUrl": "https://media.api-sports.io/football/teams/4677.png",
            "caption": "Alfreton Town crest",
            "representativeOfPage": true,
            "encodingFormat": "image/png",
            "width": 150,
            "height": 150
          }
        }
      },

      {
        "@type": "StadiumOrArena",
        "name": "St James Park",
        "maximumAttendeeCapacity": 3500,
        "latitude": 52.024613,
        "longitude": -1.144039,
        "subOrganization": {
          "@type": "SportsTeam",
          "name": "Brackley Town",
          "slogan": "The Saints",
          "memberOf": {
            "@type": "SportsOrganization",
            "name": "National League North"
          },
          "logo": {
            "@type": "ImageObject",
            "contentUrl": "https://media.api-sports.io/football/teams/4701.png",
            "caption": "Brackley Town crest",
            "representativeOfPage": true,
            "encodingFormat": "image/png",
            "width": 100,
            "height": 100
          }
        }
      },

      {
        "@type": "StadiumOrArena",
        "name": "Technique Stadium",
        "maximumAttendeeCapacity": 10600,
        "latitude": 53.253583,
        "longitude": -1.425761,
        "subOrganization": {
          "@type": "SportsTeam",
          "name": "Chesterfield",
          "slogan": "The Spireites",
          "memberOf": {
            "@type": "SportsOrganization",
            "name": "National League"
          },
          "logo": {
            "@type": "ImageObject",
            "contentUrl": "https://media.api-sports.io/football/teams/1345.png",
            "caption": "Chesterfield crest",
            "representativeOfPage": true,
            "encodingFormat": "image/png",
            "width": 150,
            "height": 150
          }
        }
      },

      {
        "@type": "StadiumOrArena",
        "name": "The Northolme",
        "alternateName": "The Dave Longstaff Martin and Co Arena",
        "maximumAttendeeCapacity": 4304,
        "latitude": 53.403459,
        "longitude": -0.774463,
        "subOrganization": {
          "@type": "SportsTeam",
          "name": "Gainsborough Trinity",
          "slogan": "The Trinity",
          "memberOf": {
            "@type": "SportsOrganization",
            "name": "Northern Premier League"
          },
          "logo": {
            "@type": "ImageObject",
            "contentUrl": "https://media.api-sports.io/football/teams/4691.png",
            "caption": "Gainsborough Trinity crest",
            "representativeOfPage": true,
            "encodingFormat": "image/png",
            "width": 150,
            "height": 150
          }
        }
      },

      {
        "@type": "StadiumOrArena",
        "name": "The Silverlands",
        "alternateName": "The Tarmac Silverlands Stadium",
        "maximumAttendeeCapacity": 4000,
        "latitude": 53.256603,
        "longitude": -1.906581,
        "subOrganization": {
          "@type": "SportsTeam",
          "name": "Buxton",
          "slogan": "The Bucks",
          "memberOf": {
            "@type": "SportsOrganization",
            "name": "National League North"
          },
          "logo": {
            "@type": "ImageObject",
            "contentUrl": "https://media.api-sports.io/football/teams/7706.png",
            "caption": "Buxton crest",
            "representativeOfPage": true,
            "encodingFormat": "image/png",
            "width": 100,
            "height": 100
          }
        }
      }
    ]
  },
  {
    "@context": "http://schema.org",
    "@type": "AdministrativeArea",
    "name": "East of England",
    "alternateName": "the East of England",
    "geoContains": [
      {
        "@type": "StadiumOrArena",
        "name": "Clarence Park",
        "alternateName": "Mozzarella Fellas Stadium",
        "maximumAttendeeCapacity": 5007,
        "latitude": 51.754276,
        "longitude": -0.325157,
        "subOrganization": {
          "@type": "SportsTeam",
          "name": "St Albans City",
          "slogan": "The Saints",
          "memberOf": {
            "@type": "SportsOrganization",
            "name": "National League South"
          },
          "logo": {
            "@type": "ImageObject",
            "contentUrl": "https://media.api-sports.io/football/teams/4708.png",
            "caption": "St Albans City crest",
            "representativeOfPage": true,
            "encodingFormat": "image/png",
            "width": 180,
            "height": 180
          }
        }
      },

      {
        "@type": "StadiumOrArena",
        "name": "Cressing Road",
        "alternateName": "Dunmow Group Stadium",
        "maximumAttendeeCapacity": 4222,
        "latitude": 51.875305,
        "longitude": 0.572989,
        "subOrganization": {
          "@type": "SportsTeam",
          "name": "Braintree Town",
          "slogan": "The Iron",
          "memberOf": {
            "@type": "SportsOrganization",
            "name": "National League South"
          },
          "logo": {
            "@type": "ImageObject",
            "contentUrl": "https://media.api-sports.io/football/teams/1831.png",
            "caption": "Braintree Town crest",
            "representativeOfPage": true,
            "encodingFormat": "image/png",
            "width": 137,
            "height": 138
          }
        }
      },

      {
        "@type": "StadiumOrArena",
        "name": "Len Salmon Stadium",
        "maximumAttendeeCapacity": 3500,
        "latitude": 51.57405,
        "longitude": 0.518133,
        "subOrganization": {
          "@type": "SportsTeam",
          "name": "Bowers & Pitsea",
          "slogan": "The Bowers",
          "memberOf": {
            "@type": "SportsOrganization",
            "name": "Isthmian League Premier Division"
          },
          "logo": {
            "@type": "ImageObject",
            "contentUrl": "https://media.api-sports.io/football/teams/7764.png",
            "caption": "Bowers & Pitsea crest",
            "representativeOfPage": true,
            "encodingFormat": "image/png",
            "width": 150,
            "height": 150
          }
        }
      },

      {
        "@type": "StadiumOrArena",
        "name": "Lincoln Road",
        "maximumAttendeeCapacity": 2300,
        "latitude": 52.593814,
        "longitude": -0.254312,
        "subOrganization": {
          "@type": "SportsTeam",
          "name": "Peterborough Sports",
          "slogan": "The Turbines",
          "memberOf": {
            "@type": "SportsOrganization",
            "name": "National League North"
          },
          "logo": {
            "@type": "ImageObject",
            "contentUrl": "https://media.api-sports.io/football/teams/7737.png",
            "caption": "Peterborough Sports crest",
            "representativeOfPage": true,
            "encodingFormat": "image/png",
            "width": 150,
            "height": 150
          }
        }
      },

      {
        "@type": "StadiumOrArena",
        "name": "Meadow Park",
        "alternateName": "LV Bet Stadium Meadow Park",
        "maximumAttendeeCapacity": 4502,
        "latitude": 51.661937,
        "longitude": -0.272375,
        "subOrganization": {
          "@type": "SportsTeam",
          "name": "Boreham Wood",
          "slogan": "The Wood",
          "memberOf": {
            "@type": "SportsOrganization",
            "name": "National League"
          },
          "logo": {
            "@type": "ImageObject",
            "contentUrl": "https://media.api-sports.io/football/teams/1830.png",
            "caption": "Boreham Wood crest",
            "representativeOfPage": true,
            "encodingFormat": "image/png",
            "width": 150,
            "height": 150
          }
        }
      },

      {
        "@type": "StadiumOrArena",
        "name": "Melbourne Stadium",
        "maximumAttendeeCapacity": 3065,
        "latitude": 51.753231,
        "longitude": 0.451471,
        "subOrganization": {
          "@type": "SportsTeam",
          "name": "Chelmsford City",
          "slogan": "The Clarets",
          "memberOf": {
            "@type": "SportsOrganization",
            "name": "National League South"
          },
          "logo": {
            "@type": "ImageObject",
            "contentUrl": "https://media.api-sports.io/football/teams/4689.png",
            "caption": "Chelmsford City crest",
            "representativeOfPage": true,
            "encodingFormat": "image/png",
            "width": 130,
            "height": 130
          }
        }
      },

      {
        "@type": "StadiumOrArena",
        "name": "New Lodge",
        "maximumAttendeeCapacity": 5000,
        "latitude": 51.621776,
        "longitude": 0.403297,
        "subOrganization": {
          "@type": "SportsTeam",
          "name": "Billericay Town",
          "slogan": "The Blues",
          "memberOf": {
            "@type": "SportsOrganization",
            "name": "Isthmian League Premier Division"
          },
          "logo": {
            "@type": "ImageObject",
            "contentUrl": "https://media.api-sports.io/football/teams/4678.png",
            "caption": "Billericay Town crest",
            "representativeOfPage": true,
            "encodingFormat": "image/png",
            "width": 100,
            "height": 100
          }
        }
      },

      {
        "@type": "StadiumOrArena",
        "name": "North Road",
        "maximumAttendeeCapacity": 1000,
        "latitude": 51.815817,
        "longitude": 1.026387,
        "subOrganization": {
          "@type": "SportsTeam",
          "name": "Brightlingsea Regent",
          "slogan": "The Rs",
          "memberOf": {
            "@type": "SportsOrganization",
            "name": "Isthmian League Premier Division"
          },
          "logo": {
            "@type": "ImageObject",
            "contentUrl": "https://media.api-sports.io/football/teams/7704.png",
            "caption": "Brightlingsea Regent crest",
            "representativeOfPage": true,
            "encodingFormat": "image/png",
            "width": 150,
            "height": 150
          }
        }
      },

      {
        "@type": "StadiumOrArena",
        "name": "Park Lane",
        "alternateName": "The Movie Starr Stadium",
        "maximumAttendeeCapacity": 4100,
        "latitude": 51.516461,
        "longitude": 0.615713,
        "subOrganization": {
          "@type": "SportsTeam",
          "name": "Canvey Island",
          "slogan": "The Gulls",
          "memberOf": {
            "@type": "SportsOrganization",
            "name": "Isthmian League Premier Division"
          },
          "logo": {
            "@type": "ImageObject",
            "contentUrl": "https://media.api-sports.io/football/teams/7623.png",
            "caption": "Canvey Island crest",
            "representativeOfPage": true,
            "encodingFormat": "image/png",
            "width": 150,
            "height": 150
          }
        }
      },

      {
        "@type": "StadiumOrArena",
        "name": "Parkfield",
        "alternateName": "The Lantern Stadium",
        "maximumAttendeeCapacity": 2500,
        "latitude": 51.696188,
        "longitude": -0.177662,
        "subOrganization": {
          "@type": "SportsTeam",
          "name": "Potters Bar Town",
          "slogan": "The Scholars",
          "memberOf": {
            "@type": "SportsOrganization",
            "name": "Isthmian League Premier Division"
          },
          "logo": {
            "@type": "ImageObject",
            "contentUrl": "https://media.api-sports.io/football/teams/7739.png",
            "caption": "Potters Bar Town crest",
            "representativeOfPage": true,
            "encodingFormat": "image/png",
            "width": 149,
            "height": 141
          }
        }
      },

      {
        "@type": "StadiumOrArena",
        "name": "Parkside",
        "maximumAttendeeCapacity": 3500,
        "latitude": 51.503481,
        "longitude": 0.261341,
        "subOrganization": {
          "@type": "SportsTeam",
          "name": "Aveley",
          "slogan": "The Millers",
          "memberOf": {
            "@type": "SportsOrganization",
            "name": "Isthmian League Premier Division"
          },
          "logo": {
            "@type": "ImageObject",
            "contentUrl": "https://media.api-sports.io/football/teams/7207.png",
            "caption": "Aveley crest",
            "representativeOfPage": true,
            "encodingFormat": "image/png",
            "width": 150,
            "height": 150
          }
        }
      },

      {
        "@type": "StadiumOrArena",
        "name": "Roots Hall",
        "maximumAttendeeCapacity": 12392,
        "latitude": 51.549008,
        "longitude": 0.701608,
        "subOrganization": {
          "@type": "SportsTeam",
          "name": "Southend United",
          "slogan": "The Shrimpers",
          "memberOf": {
            "@type": "SportsOrganization",
            "name": "National League"
          },
          "logo": {
            "@type": "ImageObject",
            "contentUrl": "https://media.api-sports.io/football/teams/1341.png",
            "caption": "Southend United crest",
            "representativeOfPage": true,
            "encodingFormat": "image/png",
            "width": 150,
            "height": 150
          }
        }
      },

      {
        "@type": "StadiumOrArena",
        "name": "Thames Road",
        "maximumAttendeeCapacity": 3300,
        "latitude": 51.512539,
        "longitude": 0.575477,
        "subOrganization": {
          "@type": "SportsTeam",
          "name": "Concord Rangers",
          "slogan": "The Beach Boys",
          "memberOf": {
            "@type": "SportsOrganization",
            "name": "National League South"
          },
          "logo": {
            "@type": "ImageObject",
            "contentUrl": "https://media.api-sports.io/football/teams/8658.png",
            "caption": "Concord Rangers crest",
            "representativeOfPage": true,
            "encodingFormat": "image/png",
            "width": 150,
            "height": 150
          }
        }
      },

      {
        "@type": "StadiumOrArena",
        "name": "The Walks Stadium",
        "maximumAttendeeCapacity": 8200,
        "latitude": 52.750067,
        "longitude": 0.407411,
        "subOrganization": {
          "@type": "SportsTeam",
          "name": "Kings Lynn Town",
          "slogan": "The Linnets",
          "memberOf": {
            "@type": "SportsOrganization",
            "name": "National League North"
          },
          "logo": {
            "@type": "ImageObject",
            "contentUrl": "https://media.api-sports.io/football/teams/8655.png",
            "caption": "Kings Lynn Town crest",
            "representativeOfPage": true,
            "encodingFormat": "image/png",
            "width": 150,
            "height": 150
          }
        }
      },

      {
        "@type": "StadiumOrArena",
        "name": "Theobalds Lane",
        "maximumAttendeeCapacity": 3500,
        "latitude": 51.694445,
        "longitude": -0.041577,
        "subOrganization": {
          "@type": "SportsTeam",
          "name": "Cheshunt",
          "slogan": "The Ambers",
          "memberOf": {
            "@type": "SportsOrganization",
            "name": "National League South"
          },
          "logo": {
            "@type": "ImageObject",
            "contentUrl": "https://media.api-sports.io/football/teams/7708.png",
            "caption": "Cheshunt crest",
            "representativeOfPage": true,
            "encodingFormat": "image/png",
            "width": 150,
            "height": 150
          }
        }
      },

      {
        "@type": "StadiumOrArena",
        "name": "Vauxhall Road",
        "maximumAttendeeCapacity": 3152,
        "latitude": 51.753881,
        "longitude": -0.444358,
        "subOrganization": {
          "@type": "SportsTeam",
          "name": "Hemel Hempstead Town",
          "slogan": "The Tudors",
          "memberOf": {
            "@type": "SportsOrganization",
            "name": "National League South"
          },
          "logo": {
            "@type": "ImageObject",
            "contentUrl": "https://media.api-sports.io/football/teams/8660.png",
            "caption": "Hemel Hempstead Town crest",
            "representativeOfPage": true,
            "encodingFormat": "image/png",
            "width": 120,
            "height": 119
          }
        }
      },

      {
        "@type": "StadiumOrArena",
        "name": "Woodside Park",
        "alternateName": "R & D Advisors UK Ltd Stadium",
        "maximumAttendeeCapacity": 4525,
        "latitude": 51.872673,
        "longitude": 0.191994,
        "subOrganization": {
          "@type": "SportsTeam",
          "name": "Bishop's Stortford",
          "slogan": "The Blues",
          "memberOf": {
            "@type": "SportsOrganization",
            "name": "Isthmian League Premier Division"
          },
          "logo": {
            "@type": "ImageObject",
            "contentUrl": "https://media.api-sports.io/football/teams/7701.png",
            "caption": "Bishop's Stortford crest",
            "representativeOfPage": true,
            "encodingFormat": "image/png",
            "width": 150,
            "height": 150
          }
        }
      }
    ]
  },
  {
    "@context": "http://schema.org",
    "@type": "AdministrativeArea",
    "name": "London",
    "alternateName": "London",
    "geoContains": [
      {
        "@type": "StadiumOrArena",
        "name": "Beveree Stadium",
        "alternateName": "The Rocket Hospitality Beveree Stadium",
        "maximumAttendeeCapacity": 3800,
        "latitude": 51.415191,
        "longitude": -0.363244,
        "subOrganization": {
          "@type": "SportsTeam",
          "name": "Hampton & Richmond Borough",
          "slogan": "The Beavers",
          "memberOf": {
            "@type": "SportsOrganization",
            "name": "National League South"
          },
          "logo": {
            "@type": "ImageObject",
            "contentUrl": "https://media.api-sports.io/football/teams/4680.png",
            "caption": "Hampton & Richmond Borough crest",
            "representativeOfPage": true,
            "encodingFormat": "image/png",
            "width": 124,
            "height": 138
          }
        }
      },

      {
        "@type": "StadiumOrArena",
        "name": "Champion Hill",
        "maximumAttendeeCapacity": 3334,
        "latitude": 51.461239,
        "longitude": -0.084018,
        "subOrganization": {
          "@type": "SportsTeam",
          "name": "Dulwich Hamlet",
          "slogan": "The Hamlet",
          "memberOf": {
            "@type": "SportsOrganization",
            "name": "National League South"
          },
          "logo": {
            "@type": "ImageObject",
            "contentUrl": "https://media.api-sports.io/football/teams/8149.png",
            "caption": "Dulwich Hamlet crest",
            "representativeOfPage": true,
            "encodingFormat": "image/png",
            "width": 120,
            "height": 160
          }
        }
      },

      {
        "@type": "StadiumOrArena",
        "name": "Coles Park",
        "alternateName": "CVS Van Hire Stadium",
        "maximumAttendeeCapacity": 2500,
        "latitude": 51.605623,
        "longitude": -0.09266,
        "subOrganization": {
          "@type": "SportsTeam",
          "name": "Haringey Borough",
          "slogan": "The Borough",
          "memberOf": {
            "@type": "SportsOrganization",
            "name": "Isthmian League Premier Division"
          },
          "logo": {
            "@type": "ImageObject",
            "contentUrl": "https://media.api-sports.io/football/teams/4681.png",
            "caption": "Haringey Borough crest",
            "representativeOfPage": true,
            "encodingFormat": "image/png",
            "width": 150,
            "height": 150
          }
        }
      },

      {
        "@type": "StadiumOrArena",
        "name": "Grosvenor Vale",
        "maximumAttendeeCapacity": 4085,
        "latitude": 51.569398,
        "longitude": -0.416594,
        "subOrganization": {
          "@type": "SportsTeam",
          "name": "Wealdstone",
          "slogan": "The Stones",
          "memberOf": {
            "@type": "SportsOrganization",
            "name": "National League"
          },
          "logo": {
            "@type": "ImageObject",
            "contentUrl": "https://media.api-sports.io/football/teams/8663.png",
            "caption": "Wealdstone crest",
            "representativeOfPage": true,
            "encodingFormat": "image/png",
            "width": 140,
            "height": 144
          }
        }
      },

      {
        "@type": "StadiumOrArena",
        "name": "Hayes Lane",
        "maximumAttendeeCapacity": 5000,
        "latitude": 51.390084,
        "longitude": 0.021091,
        "subOrganization": {
          "@type": "SportsTeam",
          "name": "Bromley",
          "slogan": "The Ravens",
          "memberOf": {
            "@type": "SportsOrganization",
            "name": "National League"
          },
          "logo": {
            "@type": "ImageObject",
            "contentUrl": "https://media.api-sports.io/football/teams/1832.png",
            "caption": "Bromley crest",
            "representativeOfPage": true,
            "encodingFormat": "image/png",
            "width": 130,
            "height": 130
          }
        }
      },

      {
        "@type": "StadiumOrArena",
        "name": "Hayes Lane",
        "maximumAttendeeCapacity": 5000,
        "latitude": 51.390084,
        "longitude": 0.021091,
        "subOrganization": {
          "@type": "SportsTeam",
          "name": "Cray Wanderers",
          "slogan": "The Wands",
          "memberOf": {
            "@type": "SportsOrganization",
            "name": "Isthmian League Premier Division"
          },
          "logo": {
            "@type": "ImageObject",
            "contentUrl": "https://media.api-sports.io/football/teams/7711.png",
            "caption": "Cray Wanderers crest",
            "representativeOfPage": true,
            "encodingFormat": "image/png",
            "width": 100,
            "height": 100
          }
        }
      },

      {
        "@type": "StadiumOrArena",
        "name": "Hornchurch Stadium",
        "maximumAttendeeCapacity": 3000,
        "latitude": 51.556557,
        "longitude": 0.23837,
        "subOrganization": {
          "@type": "SportsTeam",
          "name": "Hornchurch",
          "slogan": "The Mighty Urchins",
          "memberOf": {
            "@type": "SportsOrganization",
            "name": "Isthmian League Premier Division"
          },
          "logo": {
            "@type": "ImageObject",
            "contentUrl": "https://media.api-sports.io/football/teams/7690.png",
            "caption": "Hornchurch crest",
            "representativeOfPage": true,
            "encodingFormat": "image/png",
            "width": 150,
            "height": 150
          }
        }
      },

      {
        "@type": "StadiumOrArena",
        "name": "Imperial Fields",
        "maximumAttendeeCapacity": 3500,
        "latitude": 51.393231,
        "longitude": -0.172327,
        "subOrganization": {
          "@type": "SportsTeam",
          "name": "Kingstonian",
          "slogan": "The Ks",
          "memberOf": {
            "@type": "SportsOrganization",
            "name": "Isthmian League Premier Division"
          },
          "logo": {
            "@type": "ImageObject",
            "contentUrl": "https://media.api-sports.io/football/teams/7725.png",
            "caption": "Kingstonian crest",
            "representativeOfPage": true,
            "encodingFormat": "image/png",
            "width": 93,
            "height": 102
          }
        }
      },

      {
        "@type": "StadiumOrArena",
        "name": "King George V Arena",
        "alternateName": "The United Business Group Stadium",
        "maximumAttendeeCapacity": 2000,
        "latitude": 51.372154,
        "longitude": -0.287229,
        "subOrganization": {
          "@type": "SportsTeam",
          "name": "Corinthian-Casuals",
          "slogan": "The Casuals",
          "memberOf": {
            "@type": "SportsOrganization",
            "name": "Isthmian League Premier Division"
          },
          "logo": {
            "@type": "ImageObject",
            "contentUrl": "https://media.api-sports.io/football/teams/7710.png",
            "caption": "Corinthian-Casuals crest",
            "representativeOfPage": true,
            "encodingFormat": "image/png",
            "width": 150,
            "height": 150
          }
        }
      },

      {
        "@type": "StadiumOrArena",
        "name": "Park View Road",
        "maximumAttendeeCapacity": 4000,
        "latitude": 51.460326,
        "longitude": 0.116558,
        "subOrganization": {
          "@type": "SportsTeam",
          "name": "Welling United",
          "slogan": "The Wings",
          "memberOf": {
            "@type": "SportsOrganization",
            "name": "National League South"
          },
          "logo": {
            "@type": "ImageObject",
            "contentUrl": "https://media.api-sports.io/football/teams/8664.png",
            "caption": "Welling United crest",
            "representativeOfPage": true,
            "encodingFormat": "image/png",
            "width": 141,
            "height": 139
          }
        }
      },

      {
        "@type": "StadiumOrArena",
        "name": "Queen Elizabeth II Stadium",
        "maximumAttendeeCapacity": 2500,
        "latitude": 51.659332,
        "longitude": -0.063843,
        "subOrganization": {
          "@type": "SportsTeam",
          "name": "Enfield Town",
          "slogan": "The Towners",
          "memberOf": {
            "@type": "SportsOrganization",
            "name": "Isthmian League Premier Division"
          },
          "logo": {
            "@type": "ImageObject",
            "contentUrl": "https://media.api-sports.io/football/teams/7714.png",
            "caption": "Enfield Town crest",
            "representativeOfPage": true,
            "encodingFormat": "image/png",
            "width": 150,
            "height": 150
          }
        }
      },

      {
        "@type": "StadiumOrArena",
        "name": "The Hive Stadium",
        "maximumAttendeeCapacity": 6418,
        "latitude": 51.602623,
        "longitude": -0.291743,
        "subOrganization": {
          "@type": "SportsTeam",
          "name": "Barnet",
          "slogan": "The Bees",
          "memberOf": {
            "@type": "SportsOrganization",
            "name": "National League"
          },
          "logo": {
            "@type": "ImageObject",
            "contentUrl": "https://media.api-sports.io/football/teams/1369.png",
            "caption": "Barnet crest",
            "representativeOfPage": true,
            "encodingFormat": "image/png",
            "width": 150,
            "height": 150
          }
        }
      },

      {
        "@type": "StadiumOrArena",
        "name": "The Maurice Rebak Stadium",
        "maximumAttendeeCapacity": 1500,
        "latitude": 51.606848,
        "longitude": -0.171497,
        "subOrganization": {
          "@type": "SportsTeam",
          "name": "Wingate & Finchley",
          "slogan": "The Blues",
          "memberOf": {
            "@type": "SportsOrganization",
            "name": "Isthmian League Premier Division"
          },
          "logo": {
            "@type": "ImageObject",
            "contentUrl": "https://media.api-sports.io/football/teams/7759.png",
            "caption": "Wingate & Finchley crest",
            "representativeOfPage": true,
            "encodingFormat": "image/png",
            "width": 150,
            "height": 150
          }
        }
      },

      {
        "@type": "StadiumOrArena",
        "name": "Victoria Road",
        "alternateName": "Chigwell Construction Stadium",
        "maximumAttendeeCapacity": 6078,
        "latitude": 51.547807,
        "longitude": 0.159913,
        "subOrganization": {
          "@type": "SportsTeam",
          "name": "Dagenham & Redbridge",
          "slogan": "The Daggers",
          "memberOf": {
            "@type": "SportsOrganization",
            "name": "National League"
          },
          "logo": {
            "@type": "ImageObject",
            "contentUrl": "https://media.api-sports.io/football/teams/1821.png",
            "caption": "Dagenham & Redbridge crest",
            "representativeOfPage": true,
            "encodingFormat": "image/png",
            "width": 150,
            "height": 150
          }
        }
      },

      {
        "@type": "StadiumOrArena",
        "name": "War Memorial Sports Ground",
        "maximumAttendeeCapacity": 5000,
        "latitude": 51.369704,
        "longitude": -0.17179,
        "subOrganization": {
          "@type": "SportsTeam",
          "name": "Carshalton Athletic",
          "slogan": "The Robins",
          "memberOf": {
            "@type": "SportsOrganization",
            "name": "Isthmian League Premier Division"
          },
          "logo": {
            "@type": "ImageObject",
            "contentUrl": "https://media.api-sports.io/football/teams/7707.png",
            "caption": "Carshalton Athletic crest",
            "representativeOfPage": true,
            "encodingFormat": "image/png",
            "width": 100,
            "height": 100
          }
        }
      }
    ]
  },
  {
    "@context": "http://schema.org",
    "@type": "AdministrativeArea",
    "name": "North East",
    "alternateName": "the North East",
    "geoContains": [
      {
        "@type": "StadiumOrArena",
        "name": "Blackwell Meadows",
        "maximumAttendeeCapacity": 3281,
        "latitude": 54.509449,
        "longitude": -1.564142,
        "subOrganization": {
          "@type": "SportsTeam",
          "name": "Darlington",
          "slogan": "The Quakers",
          "memberOf": {
            "@type": "SportsOrganization",
            "name": "National League North"
          },
          "logo": {
            "@type": "ImageObject",
            "contentUrl": "https://media.api-sports.io/football/teams/8148.png",
            "caption": "Darlington crest",
            "representativeOfPage": true,
            "encodingFormat": "image/png",
            "width": 150,
            "height": 150
          }
        }
      },

      {
        "@type": "StadiumOrArena",
        "name": "Brewery Field",
        "maximumAttendeeCapacity": 3000,
        "latitude": 54.70451,
        "longitude": -1.599134,
        "subOrganization": {
          "@type": "SportsTeam",
          "name": "Spennymoor Town",
          "slogan": "The Moors",
          "memberOf": {
            "@type": "SportsOrganization",
            "name": "National League North"
          },
          "logo": {
            "@type": "ImageObject",
            "contentUrl": "https://media.api-sports.io/football/teams/3707.png",
            "caption": "Spennymoor Town crest",
            "representativeOfPage": true,
            "encodingFormat": "image/png",
            "width": 150,
            "height": 150
          }
        }
      },

      {
        "@type": "StadiumOrArena",
        "name": "Craik Park",
        "maximumAttendeeCapacity": 3000,
        "latitude": 55.155982,
        "longitude": -1.708834,
        "subOrganization": {
          "@type": "SportsTeam",
          "name": "Morpeth Town AFC",
          "slogan": "The Highwaymen",
          "memberOf": {
            "@type": "SportsOrganization",
            "name": "Northern Premier League"
          },
          "logo": {
            "@type": "ImageObject",
            "contentUrl": "https://media.api-sports.io/football/teams/7734.png",
            "caption": "Morpeth Town AFC crest",
            "representativeOfPage": true,
            "encodingFormat": "image/png",
            "width": 150,
            "height": 150
          }
        }
      },

      {
        "@type": "StadiumOrArena",
        "name": "Croft Park",
        "maximumAttendeeCapacity": 4130,
        "latitude": 55.120879,
        "longitude": -1.511217,
        "subOrganization": {
          "@type": "SportsTeam",
          "name": "Blyth Spartans AFC",
          "slogan": "The Spartans",
          "memberOf": {
            "@type": "SportsOrganization",
            "name": "National League North"
          },
          "logo": {
            "@type": "ImageObject",
            "contentUrl": "https://media.api-sports.io/football/teams/8650.png",
            "caption": "Blyth Spartans AFC crest",
            "representativeOfPage": true,
            "encodingFormat": "image/png",
            "width": 150,
            "height": 150
          }
        }
      },

      {
        "@type": "StadiumOrArena",
        "name": "Gateshead International Stadium",
        "maximumAttendeeCapacity": 11800,
        "latitude": 54.96102,
        "longitude": -1.57967,
        "subOrganization": {
          "@type": "SportsTeam",
          "name": "Gateshead",
          "slogan": "The Tynesiders",
          "memberOf": {
            "@type": "SportsOrganization",
            "name": "National League"
          },
          "logo": {
            "@type": "ImageObject",
            "contentUrl": "https://media.api-sports.io/football/teams/1823.png",
            "caption": "Gateshead crest",
            "representativeOfPage": true,
            "encodingFormat": "image/png",
            "width": 150,
            "height": 150
          }
        }
      },

      {
        "@type": "StadiumOrArena",
        "name": "Mariners Park",
        "alternateName": "1st Cloud Arena",
        "maximumAttendeeCapacity": 3500,
        "latitude": 54.974526,
        "longitude": -1.470094,
        "subOrganization": {
          "@type": "SportsTeam",
          "name": "South Shields",
          "slogan": "The Mariners",
          "memberOf": {
            "@type": "SportsOrganization",
            "name": "Northern Premier League"
          },
          "logo": {
            "@type": "ImageObject",
            "contentUrl": "https://media.api-sports.io/football/teams/7746.png",
            "caption": "South Shields crest",
            "representativeOfPage": true,
            "encodingFormat": "image/png",
            "width": 150,
            "height": 150
          }
        }
      },

      {
        "@type": "StadiumOrArena",
        "name": "Mount Pleasant",
        "maximumAttendeeCapacity": 2500,
        "latitude": 54.589177,
        "longitude": -1.016661,
        "subOrganization": {
          "@type": "SportsTeam",
          "name": "Marske United",
          "slogan": "The Seasiders",
          "memberOf": {
            "@type": "SportsOrganization",
            "name": "Northern Premier League"
          },
          "logo": {
            "@type": "ImageObject",
            "contentUrl": "https://media.api-sports.io/football/teams/7658.png",
            "caption": "Marske United crest",
            "representativeOfPage": true,
            "encodingFormat": "image/png",
            "width": 100,
            "height": 115
          }
        }
      }
    ]
  },
  {
    "@context": "http://schema.org",
    "@type": "AdministrativeArea",
    "name": "North West",
    "alternateName": "the North West",
    "geoContains": [
      {
        "@type": "StadiumOrArena",
        "name": "Alder House",
        "alternateName": "Skuna Stadium",
        "maximumAttendeeCapacity": 2500,
        "latitude": 53.523522,
        "longitude": -2.484992,
        "subOrganization": {
          "@type": "SportsTeam",
          "name": "Atherton Collieries",
          "slogan": "The Colls",
          "memberOf": {
            "@type": "SportsOrganization",
            "name": "Northern Premier League"
          },
          "logo": {
            "@type": "ImageObject",
            "contentUrl": "https://media.api-sports.io/football/teams/7694.png",
            "caption": "Atherton Collieries crest",
            "representativeOfPage": true,
            "encodingFormat": "image/png",
            "width": 150,
            "height": 150
          }
        }
      },

      {
        "@type": "StadiumOrArena",
        "name": "Boundary Park",
        "maximumAttendeeCapacity": 13513,
        "latitude": 53.555148,
        "longitude": -2.128451,
        "subOrganization": {
          "@type": "SportsTeam",
          "name": "Oldham Athletic",
          "slogan": "The Latics",
          "memberOf": {
            "@type": "SportsOrganization",
            "name": "National League"
          },
          "logo": {
            "@type": "ImageObject",
            "contentUrl": "https://media.api-sports.io/football/teams/1349.png",
            "caption": "Oldham Athletic crest",
            "representativeOfPage": true,
            "encodingFormat": "image/png",
            "width": 150,
            "height": 150
          }
        }
      },

      {
        "@type": "StadiumOrArena",
        "name": "Bower Fold",
        "maximumAttendeeCapacity": 6500,
        "latitude": 53.475337,
        "longitude": -2.043855,
        "subOrganization": {
          "@type": "SportsTeam",
          "name": "Stalybridge Celtic",
          "slogan": "The Celts",
          "memberOf": {
            "@type": "SportsOrganization",
            "name": "Northern Premier League"
          },
          "logo": {
            "@type": "ImageObject",
            "contentUrl": "https://media.api-sports.io/football/teams/7749.png",
            "caption": "Stalybridge Celtic crest",
            "representativeOfPage": true,
            "encodingFormat": "image/png",
            "width": 118,
            "height": 138
          }
        }
      },

      {
        "@type": "StadiumOrArena",
        "name": "Broadhurst Park",
        "maximumAttendeeCapacity": 4400,
        "latitude": 53.516649,
        "longitude": -2.180394,
        "subOrganization": {
          "@type": "SportsTeam",
          "name": "FC United of Manchester",
          "slogan": "The Reds",
          "memberOf": {
            "@type": "SportsOrganization",
            "name": "Northern Premier League"
          },
          "logo": {
            "@type": "ImageObject",
            "contentUrl": "https://media.api-sports.io/football/teams/7754.png",
            "caption": "FC United of Manchester crest",
            "representativeOfPage": true,
            "encodingFormat": "image/png",
            "width": 150,
            "height": 150
          }
        }
      },

      {
        "@type": "StadiumOrArena",
        "name": "Cantilever Park",
        "maximumAttendeeCapacity": 2550,
        "latitude": 53.377071,
        "longitude": -2.569861,
        "subOrganization": {
          "@type": "SportsTeam",
          "name": "Warrington Town",
          "slogan": "The Yellows",
          "memberOf": {
            "@type": "SportsOrganization",
            "name": "Northern Premier League"
          },
          "logo": {
            "@type": "ImageObject",
            "contentUrl": "https://media.api-sports.io/football/teams/7756.png",
            "caption": "Warrington Town crest",
            "representativeOfPage": true,
            "encodingFormat": "image/png",
            "width": 145,
            "height": 180
          }
        }
      },

      {
        "@type": "StadiumOrArena",
        "name": "Deva Stadium",
        "alternateName": "Swansway Chester Stadium",
        "maximumAttendeeCapacity": 5400,
        "latitude": 53.189215,
        "longitude": -2.923496,
        "subOrganization": {
          "@type": "SportsTeam",
          "name": "Chester",
          "slogan": "The Seals",
          "memberOf": {
            "@type": "SportsOrganization",
            "name": "National League North"
          },
          "logo": {
            "@type": "ImageObject",
            "contentUrl": "https://media.api-sports.io/football/teams/1820.png",
            "caption": "Chester crest",
            "representativeOfPage": true,
            "encodingFormat": "image/png",
            "width": 150,
            "height": 150
          }
        }
      },

      {
        "@type": "StadiumOrArena",
        "name": "Ewen Fields",
        "alternateName": "Project Solar Stadium",
        "maximumAttendeeCapacity": 4250,
        "latitude": 53.450616,
        "longitude": -2.068183,
        "subOrganization": {
          "@type": "SportsTeam",
          "name": "Hyde United",
          "slogan": "The Tigers",
          "memberOf": {
            "@type": "SportsOrganization",
            "name": "Northern Premier League"
          },
          "logo": {
            "@type": "ImageObject",
            "contentUrl": "https://media.api-sports.io/football/teams/4694.png",
            "caption": "Hyde United crest",
            "representativeOfPage": true,
            "encodingFormat": "image/png",
            "width": 174,
            "height": 172
          }
        }
      },

      {
        "@type": "StadiumOrArena",
        "name": "Giant Axe",
        "maximumAttendeeCapacity": 3513,
        "latitude": 54.051038,
        "longitude": -2.810882,
        "subOrganization": {
          "@type": "SportsTeam",
          "name": "Lancaster City",
          "slogan": "The Dolly Blues",
          "memberOf": {
            "@type": "SportsOrganization",
            "name": "Northern Premier League"
          },
          "logo": {
            "@type": "ImageObject",
            "contentUrl": "https://media.api-sports.io/football/teams/7726.png",
            "caption": "Lancaster City crest",
            "representativeOfPage": true,
            "encodingFormat": "image/png",
            "width": 150,
            "height": 150
          }
        }
      },

      {
        "@type": "StadiumOrArena",
        "name": "Haig Avenue",
        "maximumAttendeeCapacity": 6008,
        "latitude": 53.638109,
        "longitude": -2.978859,
        "subOrganization": {
          "@type": "SportsTeam",
          "name": "Southport",
          "slogan": "The Sandgrounders",
          "memberOf": {
            "@type": "SportsOrganization",
            "name": "National League North"
          },
          "logo": {
            "@type": "ImageObject",
            "contentUrl": "https://media.api-sports.io/football/teams/1826.png",
            "caption": "Southport crest",
            "representativeOfPage": true,
            "encodingFormat": "image/png",
            "width": 150,
            "height": 150
          }
        }
      },

      {
        "@type": "StadiumOrArena",
        "name": "Hurst Cross",
        "maximumAttendeeCapacity": 4250,
        "latitude": 53.501301,
        "longitude": -2.079707,
        "subOrganization": {
          "@type": "SportsTeam",
          "name": "Ashton United",
          "slogan": "The Robins",
          "memberOf": {
            "@type": "SportsOrganization",
            "name": "Northern Premier League"
          },
          "logo": {
            "@type": "ImageObject",
            "contentUrl": "https://media.api-sports.io/football/teams/7693.png",
            "caption": "Ashton United crest",
            "representativeOfPage": true,
            "encodingFormat": "image/png",
            "width": 150,
            "height": 150
          }
        }
      },

      {
        "@type": "StadiumOrArena",
        "name": "Mill Farm",
        "maximumAttendeeCapacity": 6000,
        "latitude": 53.797367,
        "longitude": -2.889497,
        "subOrganization": {
          "@type": "SportsTeam",
          "name": "AFC Fylde",
          "slogan": "The Coasters",
          "memberOf": {
            "@type": "SportsOrganization",
            "name": "National League North"
          },
          "logo": {
            "@type": "ImageObject",
            "contentUrl": "https://media.api-sports.io/football/teams/1839.png",
            "caption": "AFC Fylde crest",
            "representativeOfPage": true,
            "encodingFormat": "image/png",
            "width": 150,
            "height": 150
          }
        }
      },

      {
        "@type": "StadiumOrArena",
        "name": "Moss Lane",
        "alternateName": "J. Davidson Stadium",
        "maximumAttendeeCapacity": 7873,
        "latitude": 53.383434,
        "longitude": -2.335159,
        "subOrganization": {
          "@type": "SportsTeam",
          "name": "Altrincham",
          "slogan": "The Robins",
          "memberOf": {
            "@type": "SportsOrganization",
            "name": "National League"
          },
          "logo": {
            "@type": "ImageObject",
            "contentUrl": "https://media.api-sports.io/football/teams/4700.png",
            "caption": "Altrincham crest",
            "representativeOfPage": true,
            "encodingFormat": "image/png",
            "width": 150,
            "height": 150
          }
        }
      },

      {
        "@type": "StadiumOrArena",
        "name": "Rossett Park",
        "alternateName": "The Marine Travel Arena",
        "maximumAttendeeCapacity": 2150,
        "latitude": 53.485173,
        "longitude": -3.033623,
        "subOrganization": {
          "@type": "SportsTeam",
          "name": "Marine AFC",
          "slogan": "The Mariners",
          "memberOf": {
            "@type": "SportsOrganization",
            "name": "Northern Premier League"
          },
          "logo": {
            "@type": "ImageObject",
            "contentUrl": "https://media.api-sports.io/football/teams/7656.png",
            "caption": "Marine AFC crest",
            "representativeOfPage": true,
            "encodingFormat": "image/png",
            "width": 170,
            "height": 170
          }
        }
      },

      {
        "@type": "StadiumOrArena",
        "name": "Rylands Recreation Club",
        "maximumAttendeeCapacity": 1345,
        "latitude": 53.4004,
        "longitude": -2.575604,
        "subOrganization": {
          "@type": "SportsTeam",
          "name": "Warrington Rylands 1906",
          "slogan": "The Blues",
          "memberOf": {
            "@type": "SportsOrganization",
            "name": "Northern Premier League"
          },
          "logo": {
            "@type": "ImageObject",
            "contentUrl": "https://media.api-sports.io/football/teams/8918.png",
            "caption": "Warrington Rylands 1906 crest",
            "representativeOfPage": true,
            "encodingFormat": "image/png",
            "width": 150,
            "height": 150
          }
        }
      },

      {
        "@type": "StadiumOrArena",
        "name": "Sir Tom Finney Stadium",
        "maximumAttendeeCapacity": 3000,
        "latitude": 53.727892,
        "longitude": -2.671923,
        "subOrganization": {
          "@type": "SportsTeam",
          "name": "Bamber Bridge",
          "slogan": "The Brig",
          "memberOf": {
            "@type": "SportsOrganization",
            "name": "Northern Premier League"
          },
          "logo": {
            "@type": "ImageObject",
            "contentUrl": "https://media.api-sports.io/football/teams/7695.png",
            "caption": "Bamber Bridge crest",
            "representativeOfPage": true,
            "encodingFormat": "image/png",
            "width": 150,
            "height": 150
          }
        }
      },

      {
        "@type": "StadiumOrArena",
        "name": "Stainton Park",
        "alternateName": "Neuven Stadium",
        "maximumAttendeeCapacity": 4080,
        "latitude": 53.567592,
        "longitude": -2.340701,
        "subOrganization": {
          "@type": "SportsTeam",
          "name": "Radcliffe",
          "slogan": "The Boro",
          "memberOf": {
            "@type": "SportsOrganization",
            "name": "Northern Premier League"
          },
          "logo": {
            "@type": "ImageObject",
            "contentUrl": "https://media.api-sports.io/football/teams/7740.png",
            "caption": "Radcliffe crest",
            "representativeOfPage": true,
            "encodingFormat": "image/png",
            "width": 150,
            "height": 150
          }
        }
      },

      {
        "@type": "StadiumOrArena",
        "name": "Tameside Stadium",
        "maximumAttendeeCapacity": 4200,
        "latitude": 53.494258,
        "longitude": -2.116084,
        "subOrganization": {
          "@type": "SportsTeam",
          "name": "Curzon Ashton",
          "slogan": "The Nash",
          "memberOf": {
            "@type": "SportsOrganization",
            "name": "National League North"
          },
          "logo": {
            "@type": "ImageObject",
            "contentUrl": "https://media.api-sports.io/football/teams/4703.png",
            "caption": "Curzon Ashton crest",
            "representativeOfPage": true,
            "encodingFormat": "image/png",
            "width": 150,
            "height": 150
          }
        }
      },

      {
        "@type": "StadiumOrArena",
        "name": "Victory Park",
        "alternateName": "The Chorley Group Victory Park Stadium",
        "maximumAttendeeCapacity": 4300,
        "latitude": 53.645567,
        "longitude": -2.629188,
        "subOrganization": {
          "@type": "SportsTeam",
          "name": "Chorley",
          "slogan": "The Magpies",
          "memberOf": {
            "@type": "SportsOrganization",
            "name": "National League North"
          },
          "logo": {
            "@type": "ImageObject",
            "contentUrl": "https://media.api-sports.io/football/teams/4679.png",
            "caption": "Chorley crest",
            "representativeOfPage": true,
            "encodingFormat": "image/png",
            "width": 100,
            "height": 127
          }
        }
      },

      {
        "@type": "StadiumOrArena",
        "name": "Weaver Stadium",
        "alternateName": "Optimum Pay Stadium",
        "maximumAttendeeCapacity": 3500,
        "latitude": 53.072687,
        "longitude": -2.52846,
        "subOrganization": {
          "@type": "SportsTeam",
          "name": "Nantwich Town",
          "slogan": "The Dabbers",
          "memberOf": {
            "@type": "SportsOrganization",
            "name": "Northern Premier League"
          },
          "logo": {
            "@type": "ImageObject",
            "contentUrl": "https://media.api-sports.io/football/teams/4697.png",
            "caption": "Nantwich Town crest",
            "representativeOfPage": true,
            "encodingFormat": "image/png",
            "width": 188,
            "height": 180
          }
        }
      }
    ]
  },
  {
    "@context": "http://schema.org",
    "@type": "AdministrativeArea",
    "name": "South East",
    "alternateName": "the South East",
    "geoContains": [
      {
        "@type": "StadiumOrArena",
        "name": "Arbour Park",
        "maximumAttendeeCapacity": 2000,
        "latitude": 51.5198622,
        "longitude": -0.5884198,
        "subOrganization": {
          "@type": "SportsTeam",
          "name": "Slough Town",
          "slogan": "The Rebels",
          "memberOf": {
            "@type": "SportsOrganization",
            "name": "National League South"
          },
          "logo": {
            "@type": "ImageObject",
            "contentUrl": "https://media.api-sports.io/football/teams/4685.png",
            "caption": "Slough Town crest",
            "representativeOfPage": true,
            "encodingFormat": "image/png",
            "width": 150,
            "height": 150
          }
        }
      },

      {
        "@type": "StadiumOrArena",
        "name": "Cheriton Road",
        "alternateName": "The Buildkent Stadium",
        "maximumAttendeeCapacity": 4000,
        "latitude": 51.086574,
        "longitude": 1.159508,
        "subOrganization": {
          "@type": "SportsTeam",
          "name": "Folkestone Invicta",
          "slogan": "The Seasiders",
          "memberOf": {
            "@type": "SportsOrganization",
            "name": "Isthmian League Premier Division"
          },
          "logo": {
            "@type": "ImageObject",
            "contentUrl": "https://media.api-sports.io/football/teams/7716.png",
            "caption": "Folkestone Invicta crest",
            "representativeOfPage": true,
            "encodingFormat": "image/png",
            "width": 150,
            "height": 150
          }
        }
      },

      {
        "@type": "StadiumOrArena",
        "name": "Cherrywood Road",
        "alternateName": "Easy As HGV Stadium",
        "maximumAttendeeCapacity": 7000,
        "latitude": 51.310449,
        "longitude": -0.762256,
        "subOrganization": {
          "@type": "SportsTeam",
          "name": "Farnborough",
          "slogan": "Boro",
          "memberOf": {
            "@type": "SportsOrganization",
            "name": "National League South"
          },
          "logo": {
            "@type": "ImageObject",
            "contentUrl": "https://media.api-sports.io/football/teams/7715.png",
            "caption": "Farnborough crest",
            "representativeOfPage": true,
            "encodingFormat": "image/png",
            "width": 150,
            "height": 150
          }
        }
      },

      {
        "@type": "StadiumOrArena",
        "name": "Crabble Athletic Ground",
        "maximumAttendeeCapacity": 5745,
        "latitude": 51.137804,
        "longitude": 1.284943,
        "subOrganization": {
          "@type": "SportsTeam",
          "name": "Dover Athletic",
          "slogan": "The Whites",
          "memberOf": {
            "@type": "SportsOrganization",
            "name": "National League South"
          },
          "logo": {
            "@type": "ImageObject",
            "contentUrl": "https://media.api-sports.io/football/teams/1829.png",
            "caption": "Dover Athletic crest",
            "representativeOfPage": true,
            "encodingFormat": "image/png",
            "width": 150,
            "height": 150
          }
        }
      },

      {
        "@type": "StadiumOrArena",
        "name": "Gallagher Stadium",
        "maximumAttendeeCapacity": 4200,
        "latitude": 51.28002,
        "longitude": 0.516091,
        "subOrganization": {
          "@type": "SportsTeam",
          "name": "Maidstone United",
          "slogan": "The Stones",
          "memberOf": {
            "@type": "SportsOrganization",
            "name": "National League"
          },
          "logo": {
            "@type": "ImageObject",
            "contentUrl": "https://media.api-sports.io/football/teams/1825.png",
            "caption": "Maidstone United crest",
            "representativeOfPage": true,
            "encodingFormat": "image/png",
            "width": 150,
            "height": 150
          }
        }
      },

      {
        "@type": "StadiumOrArena",
        "name": "Hartsdown Park",
        "maximumAttendeeCapacity": 2100,
        "latitude": 51.380459,
        "longitude": 1.373928,
        "subOrganization": {
          "@type": "SportsTeam",
          "name": "Margate",
          "slogan": "The Gate",
          "memberOf": {
            "@type": "SportsOrganization",
            "name": "Isthmian League Premier Division"
          },
          "logo": {
            "@type": "ImageObject",
            "contentUrl": "https://media.api-sports.io/football/teams/7730.png",
            "caption": "Margate crest",
            "representativeOfPage": true,
            "encodingFormat": "image/png",
            "width": 175,
            "height": 207
          }
        }
      },

      {
        "@type": "StadiumOrArena",
        "name": "Hop Oast Stadium",
        "alternateName": "The Camping World Community Stadium",
        "maximumAttendeeCapacity": 1980,
        "latitude": 51.046893,
        "longitude": -0.340681,
        "subOrganization": {
          "@type": "SportsTeam",
          "name": "Horsham",
          "slogan": "The Hornets",
          "memberOf": {
            "@type": "SportsOrganization",
            "name": "Isthmian League Premier Division"
          },
          "logo": {
            "@type": "ImageObject",
            "contentUrl": "https://media.api-sports.io/football/teams/7723.png",
            "caption": "Horsham crest",
            "representativeOfPage": true,
            "encodingFormat": "image/png",
            "width": 150,
            "height": 150
          }
        }
      },

      {
        "@type": "StadiumOrArena",
        "name": "Kingfield Stadium",
        "alternateName": "The Laithwaite Community Stadium",
        "maximumAttendeeCapacity": 6036,
        "latitude": 51.306298,
        "longitude": -0.558875,
        "subOrganization": {
          "@type": "SportsTeam",
          "name": "Woking",
          "slogan": "The Cardinals",
          "memberOf": {
            "@type": "SportsOrganization",
            "name": "National League"
          },
          "logo": {
            "@type": "ImageObject",
            "contentUrl": "https://media.api-sports.io/football/teams/1836.png",
            "caption": "Woking crest",
            "representativeOfPage": true,
            "encodingFormat": "image/png",
            "width": 150,
            "height": 150
          }
        }
      },

      {
        "@type": "StadiumOrArena",
        "name": "Longmead Stadium",
        "alternateName": "Halcyon Wealth Longmead Stadium",
        "maximumAttendeeCapacity": 3000,
        "latitude": 51.211531,
        "longitude": 0.269116,
        "subOrganization": {
          "@type": "SportsTeam",
          "name": "Tonbridge Angels",
          "slogan": "The Angels",
          "memberOf": {
            "@type": "SportsOrganization",
            "name": "National League South"
          },
          "logo": {
            "@type": "ImageObject",
            "contentUrl": "https://media.api-sports.io/football/teams/8662.png",
            "caption": "Tonbridge Angels crest",
            "representativeOfPage": true,
            "encodingFormat": "image/png",
            "width": 150,
            "height": 150
          }
        }
      },

      {
        "@type": "StadiumOrArena",
        "name": "Marsh Lane",
        "maximumAttendeeCapacity": 3500,
        "latitude": 51.773923,
        "longitude": -1.227743,
        "subOrganization": {
          "@type": "SportsTeam",
          "name": "Oxford City",
          "slogan": "The Hoops",
          "memberOf": {
            "@type": "SportsOrganization",
            "name": "National League South"
          },
          "logo": {
            "@type": "ImageObject",
            "contentUrl": "https://media.api-sports.io/football/teams/1338.png",
            "caption": "Oxford City crest",
            "representativeOfPage": true,
            "encodingFormat": "image/png",
            "width": 150,
            "height": 150
          }
        }
      },

      {
        "@type": "StadiumOrArena",
        "name": "Meadowbank",
        "maximumAttendeeCapacity": 3000,
        "latitude": 51.234444,
        "longitude": -0.333543,
        "subOrganization": {
          "@type": "SportsTeam",
          "name": "Dorking Wanderers",
          "slogan": "The Wanderers",
          "memberOf": {
            "@type": "SportsOrganization",
            "name": "National League"
          },
          "logo": {
            "@type": "ImageObject",
            "contentUrl": "https://media.api-sports.io/football/teams/8659.png",
            "caption": "Dorking Wanderers crest",
            "representativeOfPage": true,
            "encodingFormat": "image/png",
            "width": 150,
            "height": 150
          }
        }
      },

      {
        "@type": "StadiumOrArena",
        "name": "Nyewood Lane",
        "maximumAttendeeCapacity": 4500,
        "latitude": 50.786982,
        "longitude": -0.690213,
        "subOrganization": {
          "@type": "SportsTeam",
          "name": "Bognor Regis Town",
          "slogan": "The Rocks",
          "memberOf": {
            "@type": "SportsOrganization",
            "name": "Isthmian League Premier Division"
          },
          "logo": {
            "@type": "ImageObject",
            "contentUrl": "https://media.api-sports.io/football/teams/7703.png",
            "caption": "Bognor Regis Town crest",
            "representativeOfPage": true,
            "encodingFormat": "image/png",
            "width": 126,
            "height": 138
          }
        }
      },

      {
        "@type": "StadiumOrArena",
        "name": "Princes Park",
        "alternateName": "Bericote Powerhouse Princes Park",
        "maximumAttendeeCapacity": 4100,
        "latitude": 51.437182,
        "longitude": 0.230837,
        "subOrganization": {
          "@type": "SportsTeam",
          "name": "Dartford",
          "slogan": "The Darts",
          "memberOf": {
            "@type": "SportsOrganization",
            "name": "National League South"
          },
          "logo": {
            "@type": "ImageObject",
            "contentUrl": "https://media.api-sports.io/football/teams/4690.png",
            "caption": "Dartford crest",
            "representativeOfPage": true,
            "encodingFormat": "image/png",
            "width": 120,
            "height": 129
          }
        }
      },

      {
        "@type": "StadiumOrArena",
        "name": "Priory Lane",
        "alternateName": "SO Legal Community Stadium",
        "maximumAttendeeCapacity": 7000,
        "latitude": 50.80417,
        "longitude": 0.32078,
        "subOrganization": {
          "@type": "SportsTeam",
          "name": "Eastbourne Borough",
          "slogan": "The Sports",
          "memberOf": {
            "@type": "SportsOrganization",
            "name": "National League South"
          },
          "logo": {
            "@type": "ImageObject",
            "contentUrl": "https://media.api-sports.io/football/teams/4704.png",
            "caption": "Eastbourne Borough crest",
            "representativeOfPage": true,
            "encodingFormat": "image/png",
            "width": 150,
            "height": 150
          }
        }
      },

      {
        "@type": "StadiumOrArena",
        "name": "Recreation Ground",
        "alternateName": "The EBB Stadium at the Recreation Ground",
        "maximumAttendeeCapacity": 7100,
        "latitude": 51.248415,
        "longitude": -0.754682,
        "subOrganization": {
          "@type": "SportsTeam",
          "name": "Aldershot Town",
          "slogan": "The Shots",
          "memberOf": {
            "@type": "SportsOrganization",
            "name": "National League"
          },
          "logo": {
            "@type": "ImageObject",
            "contentUrl": "https://media.api-sports.io/football/teams/1818.png",
            "caption": "Aldershot Town crest",
            "representativeOfPage": true,
            "encodingFormat": "image/png",
            "width": 150,
            "height": 150
          }
        }
      },

      {
        "@type": "StadiumOrArena",
        "name": "Spencer Stadium",
        "alternateName": "The Banbury Plant Hire Community Stadium",
        "maximumAttendeeCapacity": 6500,
        "latitude": 52.056796,
        "longitude": -1.325791,
        "subOrganization": {
          "@type": "SportsTeam",
          "name": "Banbury United",
          "slogan": "The Puritans",
          "memberOf": {
            "@type": "SportsOrganization",
            "name": "National League North"
          },
          "logo": {
            "@type": "ImageObject",
            "contentUrl": "https://media.api-sports.io/football/teams/7696.png",
            "caption": "Banbury United crest",
            "representativeOfPage": true,
            "encodingFormat": "image/png",
            "width": 100,
            "height": 93
          }
        }
      },

      {
        "@type": "StadiumOrArena",
        "name": "Stonebridge Road",
        "alternateName": "Kuflink Stadium",
        "maximumAttendeeCapacity": 4769,
        "latitude": 51.449556,
        "longitude": 0.32237,
        "subOrganization": {
          "@type": "SportsTeam",
          "name": "Ebbsfleet United",
          "slogan": "The Fleet",
          "memberOf": {
            "@type": "SportsOrganization",
            "name": "National League South"
          },
          "logo": {
            "@type": "ImageObject",
            "contentUrl": "https://media.api-sports.io/football/teams/1840.png",
            "caption": "Ebbsfleet United crest",
            "representativeOfPage": true,
            "encodingFormat": "image/png",
            "width": 150,
            "height": 150
          }
        }
      },

      {
        "@type": "StadiumOrArena",
        "name": "Ten Acres",
        "alternateName": "Silverlake Stadium",
        "maximumAttendeeCapacity": 5192,
        "latitude": 50.95229,
        "longitude": -1.372023,
        "subOrganization": {
          "@type": "SportsTeam",
          "name": "Eastleigh",
          "slogan": "The Spitfires",
          "memberOf": {
            "@type": "SportsOrganization",
            "name": "National League"
          },
          "logo": {
            "@type": "ImageObject",
            "contentUrl": "https://media.api-sports.io/football/teams/1822.png",
            "caption": "Eastleigh crest",
            "representativeOfPage": true,
            "encodingFormat": "image/png",
            "width": 130,
            "height": 130
          }
        }
      },

      {
        "@type": "StadiumOrArena",
        "name": "The Dripping Pan",
        "maximumAttendeeCapacity": 3000,
        "latitude": 50.869019,
        "longitude": 0.012321,
        "subOrganization": {
          "@type": "SportsTeam",
          "name": "Lewes",
          "slogan": "The Rooks",
          "memberOf": {
            "@type": "SportsOrganization",
            "name": "Isthmian League Premier Division"
          },
          "logo": {
            "@type": "ImageObject",
            "contentUrl": "https://media.api-sports.io/football/teams/7728.png",
            "caption": "Lewes crest",
            "representativeOfPage": true,
            "encodingFormat": "image/png",
            "width": 150,
            "height": 150
          }
        }
      },

      {
        "@type": "StadiumOrArena",
        "name": "The Pilot Field",
        "maximumAttendeeCapacity": 4050,
        "latitude": 50.874501,
        "longitude": 0.587099,
        "subOrganization": {
          "@type": "SportsTeam",
          "name": "Hastings United",
          "slogan": "The U's",
          "memberOf": {
            "@type": "SportsOrganization",
            "name": "Isthmian League Premier Division"
          },
          "logo": {
            "@type": "ImageObject",
            "contentUrl": "https://media.api-sports.io/football/teams/7231.png",
            "caption": "Hastings United crest",
            "representativeOfPage": true,
            "encodingFormat": "image/png",
            "width": 150,
            "height": 150
          }
        }
      },

      {
        "@type": "StadiumOrArena",
        "name": "Town Ground",
        "maximumAttendeeCapacity": 3034,
        "latitude": 51.408934,
        "longitude": -1.513463,
        "subOrganization": {
          "@type": "SportsTeam",
          "name": "Hungerford Town",
          "slogan": "The Crusaders",
          "memberOf": {
            "@type": "SportsOrganization",
            "name": "National League South"
          },
          "logo": {
            "@type": "ImageObject",
            "contentUrl": "https://media.api-sports.io/football/teams/8661.png",
            "caption": "Hungerford Town crest",
            "representativeOfPage": true,
            "encodingFormat": "image/png",
            "width": 150,
            "height": 150
          }
        }
      },

      {
        "@type": "StadiumOrArena",
        "name": "Westleigh Park",
        "alternateName": "Draper Tools Community Stadium",
        "maximumAttendeeCapacity": 5300,
        "latitude": 50.867087,
        "longitude": -0.974097,
        "subOrganization": {
          "@type": "SportsTeam",
          "name": "Havant & Waterlooville",
          "slogan": "The Hawks",
          "memberOf": {
            "@type": "SportsOrganization",
            "name": "National League South"
          },
          "logo": {
            "@type": "ImageObject",
            "contentUrl": "https://media.api-sports.io/football/teams/1843.png",
            "caption": "Havant & Waterlooville crest",
            "representativeOfPage": true,
            "encodingFormat": "image/png",
            "width": 135,
            "height": 138
          }
        }
      },

      {
        "@type": "StadiumOrArena",
        "name": "Winch's Field",
        "alternateName": "The MBS Stadium",
        "maximumAttendeeCapacity": 3000,
        "latitude": 51.364685,
        "longitude": 1.129948,
        "subOrganization": {
          "@type": "SportsTeam",
          "name": "Herne Bay",
          "slogan": "The Bay",
          "memberOf": {
            "@type": "SportsOrganization",
            "name": "Isthmian League Premier Division"
          },
          "logo": {
            "@type": "ImageObject",
            "contentUrl": "https://media.api-sports.io/football/teams/7232.png",
            "caption": "Herne Bay crest",
            "representativeOfPage": true,
            "encodingFormat": "image/png",
            "width": 150,
            "height": 150
          }
        }
      },

      {
        "@type": "StadiumOrArena",
        "name": "Woodside Road",
        "alternateName": "The Crucial Environmental Stadium",
        "maximumAttendeeCapacity": 4000,
        "latitude": 50.82034,
        "longitude": -0.38482,
        "subOrganization": {
          "@type": "SportsTeam",
          "name": "Worthing",
          "slogan": "The Rebels",
          "memberOf": {
            "@type": "SportsOrganization",
            "name": "National League South"
          },
          "logo": {
            "@type": "ImageObject",
            "contentUrl": "https://media.api-sports.io/football/teams/7661.png",
            "caption": "Worthing crest",
            "representativeOfPage": true,
            "encodingFormat": "image/png",
            "width": 150,
            "height": 150
          }
        }
      },

      {
        "@type": "StadiumOrArena",
        "name": "York Road",
        "maximumAttendeeCapacity": 4000,
        "latitude": 51.519889,
        "longitude": -0.717968,
        "subOrganization": {
          "@type": "SportsTeam",
          "name": "Maidenhead United",
          "slogan": "The Magpies",
          "memberOf": {
            "@type": "SportsOrganization",
            "name": "National League"
          },
          "logo": {
            "@type": "ImageObject",
            "contentUrl": "https://media.api-sports.io/football/teams/1838.png",
            "caption": "Maidenhead United crest",
            "representativeOfPage": true,
            "encodingFormat": "image/png",
            "width": 150,
            "height": 120
          }
        }
      }
    ]
  },
  {
    "@context": "http://schema.org",
    "@type": "AdministrativeArea",
    "name": "South West",
    "alternateName": "the South West",
    "geoContains": [
      {
        "@type": "StadiumOrArena",
        "name": "Bob Lucas Stadium",
        "maximumAttendeeCapacity": 6600,
        "latitude": 50.619895,
        "longitude": -2.485182,
        "subOrganization": {
          "@type": "SportsTeam",
          "name": "Weymouth",
          "slogan": "The Terras",
          "memberOf": {
            "@type": "SportsOrganization",
            "name": "National League South"
          },
          "logo": {
            "@type": "ImageObject",
            "contentUrl": "https://media.api-sports.io/football/teams/8665.png",
            "caption": "Weymouth crest",
            "representativeOfPage": true,
            "encodingFormat": "image/png",
            "width": 109,
            "height": 155
          }
        }
      },

      {
        "@type": "StadiumOrArena",
        "name": "Cygnet Stadium",
        "alternateName": "The Cygnet Health Care Stadium",
        "maximumAttendeeCapacity": 2500,
        "latitude": 51.016716,
        "longitude": -3.085107,
        "subOrganization": {
          "@type": "SportsTeam",
          "name": "Taunton Town",
          "slogan": "The Peacocks",
          "memberOf": {
            "@type": "SportsOrganization",
            "name": "National League South"
          },
          "logo": {
            "@type": "ImageObject",
            "contentUrl": "https://media.api-sports.io/football/teams/4711.png",
            "caption": "Taunton Town crest",
            "representativeOfPage": true,
            "encodingFormat": "image/png",
            "width": 150,
            "height": 150
          }
        }
      },

      {
        "@type": "StadiumOrArena",
        "name": "Hardenhuish Park",
        "maximumAttendeeCapacity": 3000,
        "latitude": 51.465604,
        "longitude": -2.128737,
        "subOrganization": {
          "@type": "SportsTeam",
          "name": "Chippenham Town",
          "slogan": "The Bluebirds",
          "memberOf": {
            "@type": "SportsOrganization",
            "name": "National League South"
          },
          "logo": {
            "@type": "ImageObject",
            "contentUrl": "https://media.api-sports.io/football/teams/8147.png",
            "caption": "Chippenham Town crest",
            "representativeOfPage": true,
            "encodingFormat": "image/png",
            "width": 150,
            "height": 150
          }
        }
      },

      {
        "@type": "StadiumOrArena",
        "name": "Huish Park",
        "maximumAttendeeCapacity": 9565,
        "latitude": 50.950234,
        "longitude": -2.673974,
        "subOrganization": {
          "@type": "SportsTeam",
          "name": "Yeovil Town",
          "slogan": "The Glovers",
          "memberOf": {
            "@type": "SportsOrganization",
            "name": "National League"
          },
          "logo": {
            "@type": "ImageObject",
            "contentUrl": "https://media.api-sports.io/football/teams/1377.png",
            "caption": "Yeovil Town crest",
            "representativeOfPage": true,
            "encodingFormat": "image/png",
            "width": 150,
            "height": 150
          }
        }
      },

      {
        "@type": "StadiumOrArena",
        "name": "New Meadow Park",
        "alternateName": "TigerTurf Stadium",
        "maximumAttendeeCapacity": 4000,
        "latitude": 51.860324,
        "longitude": -2.262623,
        "subOrganization": {
          "@type": "SportsTeam",
          "name": "Gloucester City AFC",
          "slogan": "The Tigers",
          "memberOf": {
            "@type": "SportsOrganization",
            "name": "National League North"
          },
          "logo": {
            "@type": "ImageObject",
            "contentUrl": "https://media.api-sports.io/football/teams/8653.png",
            "caption": "Gloucester City AFC crest",
            "representativeOfPage": true,
            "encodingFormat": "image/png",
            "width": 150,
            "height": 150
          }
        }
      },

      {
        "@type": "StadiumOrArena",
        "name": "Plainmoor",
        "maximumAttendeeCapacity": 6104,
        "latitude": 50.476389,
        "longitude": -3.523874,
        "subOrganization": {
          "@type": "SportsTeam",
          "name": "Torquay United AFC",
          "slogan": "The Gulls",
          "memberOf": {
            "@type": "SportsOrganization",
            "name": "National League"
          },
          "logo": {
            "@type": "ImageObject",
            "contentUrl": "https://media.api-sports.io/football/teams/1827.png",
            "caption": "Torquay United AFC crest",
            "representativeOfPage": true,
            "encodingFormat": "image/png",
            "width": 150,
            "height": 150
          }
        }
      },

      {
        "@type": "StadiumOrArena",
        "name": "Twerton Park",
        "maximumAttendeeCapacity": 3528,
        "latitude": 51.378847,
        "longitude": -2.395037,
        "subOrganization": {
          "@type": "SportsTeam",
          "name": "Bath City",
          "slogan": "The Romans",
          "memberOf": {
            "@type": "SportsOrganization",
            "name": "National League South"
          },
          "logo": {
            "@type": "ImageObject",
            "contentUrl": "https://media.api-sports.io/football/teams/8657.png",
            "caption": "Bath City crest",
            "representativeOfPage": true,
            "encodingFormat": "image/png",
            "width": 150,
            "height": 150
          }
        }
      }
    ]
  },
  {
    "@context": "http://schema.org",
    "@type": "AdministrativeArea",
    "name": "Wales",
    "alternateName": "Wales",
    "geoContains": [
      {
        "@type": "StadiumOrArena",
        "name": "Racecourse Ground",
        "maximumAttendeeCapacity": 10500,
        "latitude": 53.051961,
        "longitude": -3.003804,
        "subOrganization": {
          "@type": "SportsTeam",
          "name": "Wrexham AFC",
          "slogan": "The Red Dragons",
          "memberOf": {
            "@type": "SportsOrganization",
            "name": "National League"
          },
          "logo": {
            "@type": "ImageObject",
            "contentUrl": "https://media.api-sports.io/football/teams/1837.png",
            "caption": "Wrexham AFC crest",
            "representativeOfPage": true,
            "encodingFormat": "image/png",
            "width": 150,
            "height": 150
          }
        }
      }
    ]
  },
  {
    "@context": "http://schema.org",
    "@type": "AdministrativeArea",
    "name": "West Midlands",
    "alternateName": "the West Midlands",
    "geoContains": [
      {
        "@type": "StadiumOrArena",
        "name": "Aggborough",
        "maximumAttendeeCapacity": 6238,
        "latitude": 52.380496,
        "longitude": -2.242639,
        "subOrganization": {
          "@type": "SportsTeam",
          "name": "Kidderminster Harriers",
          "slogan": "The Kiddy",
          "memberOf": {
            "@type": "SportsOrganization",
            "name": "National League North"
          },
          "logo": {
            "@type": "ImageObject",
            "contentUrl": "https://media.api-sports.io/football/teams/4695.png",
            "caption": "Kidderminster Harriers crest",
            "representativeOfPage": true,
            "encodingFormat": "image/png",
            "width": 150,
            "height": 150
          }
        }
      },

      {
        "@type": "StadiumOrArena",
        "name": "Damson Park",
        "alternateName": "ARMCO Arena",
        "maximumAttendeeCapacity": 4510,
        "latitude": 52.43892,
        "longitude": -1.75719,
        "subOrganization": {
          "@type": "SportsTeam",
          "name": "Solihull Moors",
          "slogan": "The Moors",
          "memberOf": {
            "@type": "SportsOrganization",
            "name": "National League"
          },
          "logo": {
            "@type": "ImageObject",
            "contentUrl": "https://media.api-sports.io/football/teams/1834.png",
            "caption": "Solihull Moors crest",
            "representativeOfPage": true,
            "encodingFormat": "image/png",
            "width": 150,
            "height": 144
          }
        }
      },

      {
        "@type": "StadiumOrArena",
        "name": "Edgar Street",
        "maximumAttendeeCapacity": 4913,
        "latitude": 52.06073,
        "longitude": -2.71774,
        "subOrganization": {
          "@type": "SportsTeam",
          "name": "Hereford",
          "slogan": "The Bulls",
          "memberOf": {
            "@type": "SportsOrganization",
            "name": "National League North"
          },
          "logo": {
            "@type": "ImageObject",
            "contentUrl": "https://media.api-sports.io/football/teams/4692.png",
            "caption": "Hereford crest",
            "representativeOfPage": true,
            "encodingFormat": "image/png",
            "width": 150,
            "height": 150
          }
        }
      },

      {
        "@type": "StadiumOrArena",
        "name": "Marston Road",
        "maximumAttendeeCapacity": 4000,
        "latitude": 52.818555,
        "longitude": -2.116846,
        "subOrganization": {
          "@type": "SportsTeam",
          "name": "Stafford Rangers",
          "slogan": "The Rangers",
          "memberOf": {
            "@type": "SportsOrganization",
            "name": "Northern Premier League"
          },
          "logo": {
            "@type": "ImageObject",
            "contentUrl": "https://media.api-sports.io/football/teams/7748.png",
            "caption": "Stafford Rangers crest",
            "representativeOfPage": true,
            "encodingFormat": "image/png",
            "width": 116,
            "height": 138
          }
        }
      },

      {
        "@type": "StadiumOrArena",
        "name": "New Bucks Head",
        "maximumAttendeeCapacity": 6400,
        "latitude": 52.697376,
        "longitude": -2.501418,
        "subOrganization": {
          "@type": "SportsTeam",
          "name": "AFC Telford United",
          "slogan": "The Bucks",
          "memberOf": {
            "@type": "SportsOrganization",
            "name": "National League North"
          },
          "logo": {
            "@type": "ImageObject",
            "contentUrl": "https://media.api-sports.io/football/teams/4688.png",
            "caption": "AFC Telford United crest",
            "representativeOfPage": true,
            "encodingFormat": "image/png",
            "width": 150,
            "height": 150
          }
        }
      },

      {
        "@type": "StadiumOrArena",
        "name": "New Windmill Ground",
        "alternateName": "Your Co-Op Community Stadium",
        "maximumAttendeeCapacity": 2300,
        "latitude": 52.244306,
        "longitude": -1.502849,
        "subOrganization": {
          "@type": "SportsTeam",
          "name": "Leamington",
          "slogan": "The Brakes",
          "memberOf": {
            "@type": "SportsOrganization",
            "name": "National League North"
          },
          "logo": {
            "@type": "ImageObject",
            "contentUrl": "https://media.api-sports.io/football/teams/8656.png",
            "caption": "Leamington crest",
            "representativeOfPage": true,
            "encodingFormat": "image/png",
            "width": 218,
            "height": 217
          }
        }
      }
    ]
  },
  {
    "@context": "http://schema.org",
    "@type": "AdministrativeArea",
    "name": "Yorkshire and The Humber",
    "alternateName": "Yorkshire and The Humber",
    "geoContains": [
      {
        "@type": "StadiumOrArena",
        "name": "Clayborn Ground",
        "maximumAttendeeCapacity": 2000,
        "latitude": 53.717658,
        "longitude": -1.711748,
        "subOrganization": {
          "@type": "SportsTeam",
          "name": "Liversedge",
          "slogan": "The Sedge",
          "memberOf": {
            "@type": "SportsOrganization",
            "name": "Northern Premier League"
          },
          "logo": {
            "@type": "ImageObject",
            "contentUrl": "https://media.api-sports.io/football/teams/8853.png",
            "caption": "Liversedge crest",
            "representativeOfPage": true,
            "encodingFormat": "image/png",
            "width": 150,
            "height": 150
          }
        }
      },

      {
        "@type": "StadiumOrArena",
        "name": "Flamingo Land Stadium",
        "maximumAttendeeCapacity": 3252,
        "latitude": 54.268845,
        "longitude": -0.413472,
        "subOrganization": {
          "@type": "SportsTeam",
          "name": "Scarborough Athletic",
          "slogan": "The Seadogs",
          "memberOf": {
            "@type": "SportsOrganization",
            "name": "National League North"
          },
          "logo": {
            "@type": "ImageObject",
            "contentUrl": "https://media.api-sports.io/football/teams/7745.png",
            "caption": "Scarborough Athletic crest",
            "representativeOfPage": true,
            "encodingFormat": "image/png",
            "width": 150,
            "height": 150
          }
        }
      },

      {
        "@type": "StadiumOrArena",
        "name": "Glanford Park",
        "maximumAttendeeCapacity": 9088,
        "latitude": 53.5866564,
        "longitude": -0.6953374,
        "subOrganization": {
          "@type": "SportsTeam",
          "name": "Scunthorpe United",
          "slogan": "The Iron",
          "memberOf": {
            "@type": "SportsOrganization",
            "name": "National League"
          },
          "logo": {
            "@type": "ImageObject",
            "contentUrl": "https://media.api-sports.io/football/teams/1340.png",
            "caption": "Scunthorpe United crest",
            "representativeOfPage": true,
            "encodingFormat": "image/png",
            "width": 150,
            "height": 150
          }
        }
      },

      {
        "@type": "StadiumOrArena",
        "name": "Horsfall Community Stadium",
        "maximumAttendeeCapacity": 3500,
        "latitude": 53.758876,
        "longitude": -1.776174,
        "subOrganization": {
          "@type": "SportsTeam",
          "name": "Bradford (Park Avenue) AFC",
          "slogan": "The Green Army",
          "memberOf": {
            "@type": "SportsOrganization",
            "name": "National League North"
          },
          "logo": {
            "@type": "ImageObject",
            "contentUrl": "https://media.api-sports.io/football/teams/8651.png",
            "caption": "Bradford (Park Avenue) AFC crest",
            "representativeOfPage": true,
            "encodingFormat": "image/png",
            "width": 105,
            "height": 95
          }
        }
      },

      {
        "@type": "StadiumOrArena",
        "name": "Nethermoor Park",
        "maximumAttendeeCapacity": 4021,
        "latitude": 53.877202,
        "longitude": -1.719401,
        "subOrganization": {
          "@type": "SportsTeam",
          "name": "Guiseley AFC",
          "slogan": "The Lions",
          "memberOf": {
            "@type": "SportsOrganization",
            "name": "Northern Premier League"
          },
          "logo": {
            "@type": "ImageObject",
            "contentUrl": "https://media.api-sports.io/football/teams/1824.png",
            "caption": "Guiseley AFC crest",
            "representativeOfPage": true,
            "encodingFormat": "image/png",
            "width": 150,
            "height": 150
          }
        }
      },

      {
        "@type": "StadiumOrArena",
        "name": "The Citadel",
        "maximumAttendeeCapacity": 3900,
        "latitude": 53.80972,
        "longitude": -1.664219,
        "subOrganization": {
          "@type": "SportsTeam",
          "name": "Farsley Celtic",
          "slogan": "The Celt Army",
          "memberOf": {
            "@type": "SportsOrganization",
            "name": "National League North"
          },
          "logo": {
            "@type": "ImageObject",
            "contentUrl": "https://media.api-sports.io/football/teams/8652.png",
            "caption": "Farsley Celtic crest",
            "representativeOfPage": true,
            "encodingFormat": "image/png",
            "width": 150,
            "height": 150
          }
        }
      },

      {
        "@type": "StadiumOrArena",
        "name": "The Shay",
        "maximumAttendeeCapacity": 10401,
        "latitude": 53.716191,
        "longitude": -1.859217,
        "subOrganization": {
          "@type": "SportsTeam",
          "name": "FC Halifax Town",
          "slogan": "The Shaymen",
          "memberOf": {
            "@type": "SportsOrganization",
            "name": "National League"
          },
          "logo": {
            "@type": "ImageObject",
            "contentUrl": "https://media.api-sports.io/football/teams/1841.png",
            "caption": "FC Halifax Town crest",
            "representativeOfPage": true,
            "encodingFormat": "image/png",
            "width": 150,
            "height": 150
          }
        }
      },

      {
        "@type": "StadiumOrArena",
        "name": "Turnbull Ground",
        "alternateName": "Towbar Express Stadium",
        "maximumAttendeeCapacity": 3500,
        "latitude": 54.489984,
        "longitude": -0.627549,
        "subOrganization": {
          "@type": "SportsTeam",
          "name": "Whitby Town",
          "slogan": "The Seasiders",
          "memberOf": {
            "@type": "SportsOrganization",
            "name": "Northern Premier League"
          },
          "logo": {
            "@type": "ImageObject",
            "contentUrl": "https://media.api-sports.io/football/teams/7757.png",
            "caption": "Whitby Town crest",
            "representativeOfPage": true,
            "encodingFormat": "image/png",
            "width": 120,
            "height": 145
          }
        }
      },

      {
        "@type": "StadiumOrArena",
        "name": "York Community Stadium",
        "alternateName": "LNER Community Stadium",
        "maximumAttendeeCapacity": 8005,
        "latitude": 53.98434,
        "longitude": -1.052927,
        "subOrganization": {
          "@type": "SportsTeam",
          "name": "York City",
          "slogan": "The Minstermen",
          "memberOf": {
            "@type": "SportsOrganization",
            "name": "National League"
          },
          "logo": {
            "@type": "ImageObject",
            "contentUrl": "https://media.api-sports.io/football/teams/1828.png",
            "caption": "York City crest",
            "representativeOfPage": true,
            "encodingFormat": "image/png",
            "width": 150,
            "height": 150
          }
        }
      }
    ]
  }
]
